avl/__init__.py
avl/_core/__init__.py
avl/_core/agent.py
avl/_core/bool.py
avl/_core/component.py
avl/_core/coverage.py
avl/_core/coverbin.py
avl/_core/covercross.py
avl/_core/covergroup.py
avl/_core/coverpoint.py
avl/_core/driver.py
avl/_core/enum.py
avl/_core/env.py
avl/_core/factory.py
avl/_core/fifo.py
avl/_core/float.py
avl/_core/int.py
avl/_core/list.py
avl/_core/log.py
avl/_core/logic.py
avl/_core/memory.py
avl/_core/model.py
avl/_core/monitor.py
avl/_core/object.py
avl/_core/phase.py
avl/_core/phase_manager.py
avl/_core/port.py
avl/_core/scoreboard.py
avl/_core/scoreboard_indexed.py
avl/_core/sequence.py
avl/_core/sequence_item.py
avl/_core/sequencer.py
avl/_core/struct.py
avl/_core/trace.py
avl/_core/transaction.py
avl/_core/uint.py
avl/_core/var.py
avl/_core/visualization.py
avl/templates/__init__.py
avl/templates/_vanilla.py
avl/tools/coverage_analysis.py
avl/tools/trace_analysis.py
avl_core-0.4.3.dist-info/METADATA
avl_core-0.4.3.dist-info/WHEEL
avl_core-0.4.3.dist-info/entry_points.txt
avl_core-0.4.3.dist-info/licenses/LICENSE
avl_core-0.4.3.dist-info/RECORD
