Metadata-Version: 2.4
Name: avl-core
Version: 0.4.3
Summary: Apheleia Verification Library. A set of Python base classes for efficient HDL verification.
License: MIT License
License-File: LICENSE
Author: avl
Author-email: avl@projectapheleia.net
Maintainer: avl
Maintainer-email: avl@projectapheleia.net
Requires-Python: >=3.10
Classifier: Development Status :: 4 - Beta
Classifier: Programming Language :: Python
Provides-Extra: dev
Requires-Dist: anytree (>=2.13.0)
Requires-Dist: bincopy (>=20.1.0)
Requires-Dist: black (>=22.3.0) ; extra == "dev"
Requires-Dist: cocotb (>=2.0.0)
Requires-Dist: graphviz (>=0.20.3)
Requires-Dist: matplotlib (>=3.10.0) ; extra == "dev"
Requires-Dist: mypy (>=0.910) ; extra == "dev"
Requires-Dist: pandas (>=2.2.3)
Requires-Dist: pytest (>=7.0) ; extra == "dev"
Requires-Dist: pyyml (>=0.0.2)
Requires-Dist: ruff (>=0.11.0) ; extra == "dev"
Requires-Dist: sphinx (>=8.1.3) ; extra == "dev"
Requires-Dist: sphinx_rtd_theme (>=3.0.2) ; extra == "dev"
Requires-Dist: tabulate (>=0.9.0)
Requires-Dist: z3-solver (>=4.15.0.0)
